setup.py
Pytoad.egg-info/PKG-INFO
Pytoad.egg-info/SOURCES.txt
Pytoad.egg-info/dependency_links.txt
Pytoad.egg-info/requires.txt
Pytoad.egg-info/top_level.txt
pytoad/__init__.py
pytoad/connection.py
pytoad/decorator.py
pytoad/environment.py
tests/__init__.py
tests/test_connection.py
tests/test_decorator.py
tests/test_environment.py