Metadata-Version: 1.0
Name: Pytoad
Version: 1.0.3
Summary: Pytoad is a lightweight Hoptoad notifier for Python.
Home-page: https://github.com/attachmentsme/Pytoad
Author: Benjamin Coe
Author-email: ben@attachments.me
License: UNKNOWN
Platform: UNKNOWN
